odoo/addons/partner_sale_pivot/README.rst
odoo/addons/partner_sale_pivot/__init__.py
odoo/addons/partner_sale_pivot/__manifest__.py
odoo/addons/partner_sale_pivot/i18n/ca.po
odoo/addons/partner_sale_pivot/i18n/ca_ES.po
odoo/addons/partner_sale_pivot/i18n/es.po
odoo/addons/partner_sale_pivot/i18n/partner_sale_pivot.pot
odoo/addons/partner_sale_pivot/readme/CONTRIBUTORS.rst
odoo/addons/partner_sale_pivot/readme/DESCRIPTION.rst
odoo/addons/partner_sale_pivot/readme/USAGE.rst
odoo/addons/partner_sale_pivot/static/description/icon.png
odoo/addons/partner_sale_pivot/static/description/index.html
odoo/addons/partner_sale_pivot/views/res_partner_views.xml
odoo/addons/partner_sale_pivot/views/sale_report_views.xml
odoo12_addon_partner_sale_pivot-12.0.1.0.0.99.dev10.dist-info/METADATA
odoo12_addon_partner_sale_pivot-12.0.1.0.0.99.dev10.dist-info/WHEEL
odoo12_addon_partner_sale_pivot-12.0.1.0.0.99.dev10.dist-info/top_level.txt
odoo12_addon_partner_sale_pivot-12.0.1.0.0.99.dev10.dist-info/RECORD
